b2aiprep/__init__.py
b2aiprep/_version.py
b2aiprep/cli.py
b2aiprep/commands.py
b2aiprep/create_audio_files.py
b2aiprep/prepare_synthetic.py
b2aiprep/synthetic_data.py
b2aiprep/dashboard/app.py
b2aiprep/dashboard/entrypoint.py
b2aiprep/dashboard/utils.py
b2aiprep/dashboard/pages/1_Demographics.py
b2aiprep/dashboard/pages/2_Subject_Questionnaires.py
b2aiprep/dashboard/pages/3_Audio.py
b2aiprep/dashboard/pages/4_Search.py
b2aiprep/dashboard/pages/5_Validate.py
b2aiprep/dashboard/pages/summary.py
b2aiprep/prepare/__init__.py
b2aiprep/prepare/bids.py
b2aiprep/prepare/bundle_data.py
b2aiprep/prepare/constants.py
b2aiprep/prepare/data_validation.py
b2aiprep/prepare/dataset.py
b2aiprep/prepare/demographics.py
b2aiprep/prepare/fhir_utils.py
b2aiprep/prepare/phenotype.py
b2aiprep/prepare/prepare.py
b2aiprep/prepare/quality_control.py
b2aiprep/prepare/redcap.py
b2aiprep/prepare/update.py
b2aiprep/prepare/utils.py
b2aiprep/prepare/resources/__init__.py
b2aiprep/prepare/resources/all_columns.json
b2aiprep/prepare/resources/bids_field_organization.csv
b2aiprep/prepare/resources/column_mapping.json
b2aiprep/prepare/resources/column_mapping_labels_to_coded.json
b2aiprep/prepare/resources/data_validation_ranges.json
b2aiprep/prepare/resources/field_remap.json
b2aiprep/prepare/resources/phenotype_json_descriptions.py
b2aiprep/prepare/resources/questionnaire2schema.json
b2aiprep/prepare/resources/redcap_race_mapping.json
b2aiprep/prepare/resources/static_features.json
b2aiprep/prepare/resources/unique_recordings.json
b2aiprep/prepare/resources/feature_schemas/ppgs.json
b2aiprep/prepare/resources/feature_schemas/sparc_ema.json
b2aiprep/prepare/resources/feature_schemas/sparc_loudness.json
b2aiprep/prepare/resources/feature_schemas/sparc_periodicity.json
b2aiprep/prepare/resources/feature_schemas/sparc_pitch.json
b2aiprep/prepare/resources/feature_schemas/torchaudio_mel_spectrogram.json
b2aiprep/prepare/resources/feature_schemas/torchaudio_mfcc.json
b2aiprep-3.0.2.dist-info/licenses/LICENSE
b2aiprep-3.0.2.dist-info/METADATA
b2aiprep-3.0.2.dist-info/WHEEL
b2aiprep-3.0.2.dist-info/entry_points.txt
b2aiprep-3.0.2.dist-info/top_level.txt
b2aiprep-3.0.2.dist-info/RECORD
