Metadata-Version: 2.4
Name: b2aiprep
Version: 3.0.2
Summary: A small package to generate features from acoustic
Author-email: Rahul Brito <rfbrito@mit.edu>, SenseIn Group <sensein-social@mit.edu>
License: Apache License
Project-URL: Homepage, https://github.com/sensein/b2aiprep
Project-URL: Issues, https://github.com/sensein/b2aiprep/issues
Classifier: Development Status :: 3 - Alpha
Classifier: Programming Language :: Python :: 3
Classifier: License :: OSI Approved :: Apache Software License
Classifier: Operating System :: OS Independent
Requires-Python: <3.14,>=3.10
License-File: LICENSE
Requires-Dist: senselab[articulatory]~=1.3.0
Requires-Dist: matplotlib>=3.8.3
Requires-Dist: fhir.resources==7.1.0
Requires-Dist: streamlit>=1.42.2
Requires-Dist: av~=14.1.0
Requires-Dist: soundfile
Requires-Dist: pydra
Requires-Dist: torchaudio~=2.8.0
Requires-Dist: torch~=2.8.0
Requires-Dist: torchvision~=0.23.0
Provides-Extra: doc
Requires-Dist: jupyterlab; extra == "doc"
Requires-Dist: jupytext; extra == "doc"
Requires-Dist: ipympl; extra == "doc"
Provides-Extra: dev
Requires-Dist: b2aiprep[doc]; extra == "dev"
Requires-Dist: pytest; extra == "dev"
Requires-Dist: pytest-benchmark; extra == "dev"
Requires-Dist: pre-commit; extra == "dev"
Requires-Dist: ruff; extra == "dev"
Requires-Dist: responses; extra == "dev"
Requires-Dist: senselab[audio]; extra == "dev"
Provides-Extra: dashboard
Requires-Dist: b2aiprep[doc]; extra == "dashboard"
Requires-Dist: streamlit>=1.42.2; extra == "dashboard"
Requires-Dist: senselab[audio]; extra == "dashboard"
Dynamic: license-file
